z3cform.locationwidget-1.1.0-py3.8-nspkg.pth
z3cform.locationwidget-1.1.0.dist-info/METADATA
z3cform.locationwidget-1.1.0.dist-info/WHEEL
z3cform.locationwidget-1.1.0.dist-info/pydist.json
z3cform.locationwidget-1.1.0.dist-info/RECORD
z3cform.locationwidget-1.1.0.dist-info/top_level.txt
z3cform.locationwidget-1.1.0.dist-info/DESCRIPTION.rst
z3cform.locationwidget-1.1.0.dist-info/entry_points.txt
z3cform.locationwidget-1.1.0.dist-info/namespace_packages.txt
z3cform/locationwidget/__init__.py
z3cform/locationwidget/interfaces.py
z3cform/locationwidget/location_display.pt
z3cform/locationwidget/configure.zcml
z3cform/locationwidget/widget.py
z3cform/locationwidget/testing.py
z3cform/locationwidget/field.py
z3cform/locationwidget/setuphandlers.py
z3cform/locationwidget/location_input.pt
z3cform/locationwidget/tests/__init__.py
z3cform/locationwidget/tests/test_setup.py
z3cform/locationwidget/tests/test_robot.py
z3cform/locationwidget/tests/robot/test_example.robot
z3cform/locationwidget/profiles/uninstall/browserlayer.xml
z3cform/locationwidget/profiles/default/registry.xml
z3cform/locationwidget/profiles/default/browserlayer.xml
z3cform/locationwidget/profiles/default/metadata.xml
z3cform/locationwidget/profiles/default/controlpanel.xml
z3cform/locationwidget/locales/compile.sh
z3cform/locationwidget/locales/update.sh
z3cform/locationwidget/locales/z3cform.locationwidget.pot
z3cform/locationwidget/locales/ca/LC_MESSAGES/z3cform.locationwidget.po
z3cform/locationwidget/locales/ca/LC_MESSAGES/z3cform.locationwidget.mo
z3cform/locationwidget/locales/es/LC_MESSAGES/z3cform.locationwidget.po
z3cform/locationwidget/locales/es/LC_MESSAGES/z3cform.locationwidget.mo
z3cform/locationwidget/locales/fr/LC_MESSAGES/z3cform.locationwidget.po
z3cform/locationwidget/locales/fr/LC_MESSAGES/z3cform.locationwidget.mo
z3cform/locationwidget/browser/__init__.py
z3cform/locationwidget/browser/configure.zcml
z3cform/locationwidget/browser/controlpanel.py
z3cform/locationwidget/browser/overrides/.gitkeep
z3cform/locationwidget/browser/static/.gitkeep
z3cform/locationwidget/browser/static/gmaps.js
