Metadata-Version: 2.0
Name: z3cform.locationwidget
Version: 1.1.0
Summary: GMaps Widget for string fields
Home-page: https://github.com/aormazabal/z3cform.locationwidget
Author: Albert Ormazabal Blanc
Author-email: aormazabal@tda.ad
License: GPL version 2
Project-URL: PyPI, https://pypi.python.org/pypi/z3cform.locationwidget
Project-URL: Source, https://github.com/aormazabal/z3cform.locationwidget
Project-URL: Tracker, https://github.com/aormazabal/z3cform.locationwidget/issues
Keywords: Python Plone
Classifier: Environment :: Web Environment
Classifier: Framework :: Plone
Classifier: Framework :: Plone :: Addon
Classifier: Framework :: Plone :: 5.2
Classifier: Programming Language :: Python
Classifier: Programming Language :: Python :: 3.6
Classifier: Programming Language :: Python :: 3.7
Classifier: Programming Language :: Python :: 3.8
Classifier: Programming Language :: Python :: 3.9
Classifier: Operating System :: OS Independent
Classifier: License :: OSI Approved :: GNU General Public License v2 (GPLv2)
Requires-Python: >=3.6
Provides-Extra: test
Requires-Dist: setuptools
Requires-Dist: z3c.jbot
Requires-Dist: plone.api (>=1.8.4)
Requires-Dist: plone.restapi
Requires-Dist: plone.app.dexterity
Provides-Extra: test
Requires-Dist: plone.app.testing; extra == 'test'
Requires-Dist: plone.testing (>=5.0.0); extra == 'test'
Requires-Dist: plone.app.contenttypes; extra == 'test'
Requires-Dist: plone.app.robotframework[debug]; extra == 'test'
